textui/__init__.py
textui/uibuilder.py
textui/uielements.py
textui/uierrors.py
textui/uiutils.py
textui-0.2.dist-info/DESCRIPTION.rst
textui-0.2.dist-info/METADATA
textui-0.2.dist-info/RECORD
textui-0.2.dist-info/WHEEL
textui-0.2.dist-info/metadata.json
textui-0.2.dist-info/top_level.txt
