Metadata-Version: 2.0
Name: textui
Version: 0.2
Summary: A text-based UI system
Home-page: https://github.com/firsttempora/Python-textui
Author: Josh Laughner (firsttempora)
Author-email: first.tempora@gmail.com
License: UNKNOWN
Download-URL: https://github.com/firsttempora/Python-textui/tarball/0.2
Keywords: UI,user interface,text-based
Platform: UNKNOWN
Classifier: License :: OSI Approved :: MIT License
Requires-Dist: backports.shutil-get-terminal-size
